<annotation>
  <folder/>
  <filename>small_(326).jpg</filename>
  <database/>
  <annotation/>
  <image/>
  <size>
    <height>1266</height>
    <width>800</width>
    <depth>3</depth>
  </size>
  <segmented/>
  <object>
    <name>fire</name>
    <pose/>
    <truncated/>
    <difficult/>
    <bndbox>
      <xmin>64.63157894736844</xmin>
      <ymin>92.36842105263158</ymin>
      <xmax>244.8947368421052</xmax>
      <ymax>643.6842105263158</ymax>
    </bndbox>
  </object>
  <object>
    <name>fire</name>
    <pose/>
    <truncated/>
    <difficult/>
    <bndbox>
      <xmin>342.2631578947369</xmin>
      <ymin>23.94736842105263</ymin>
      <xmax>530.421052631579</xmax>
      <ymax>663.421052631579</ymax>
    </bndbox>
  </object>
  <object>
    <name>fire</name>
    <pose/>
    <truncated/>
    <difficult/>
    <bndbox>
      <xmin>614.6315789473683</xmin>
      <ymin>164.73684210526315</ymin>
      <xmax>765.9473684210527</xmax>
      <ymax>683.1578947368421</ymax>
    </bndbox>
  </object>
</annotation>
